Metadata-Version: 1.0
Name: FE-777
Version: 0.0.0
Summary: FE_777
Home-page: https://github.com/RunxingZhong/stacking_automl_001
Author: zhongrunxinig
Author-email: zhongrunxing@gmail.com
License: MIT
Platform: UNKNOWN
